setup.cfg
setup.py
bin/registrar
registrar/__init__.py
registrar/basic_wallet.py
registrar/blockchain.py
registrar/config.py
registrar/config_local.py
registrar/db.py
registrar/nameops.py
registrar/network.py
registrar/queue.py
registrar/rpc_daemon.py
registrar/server.py
registrar/states.py
registrar/subsidized_nameops.py
registrar/utils.py
registrar/wallet.py
registrar.egg-info/PKG-INFO
registrar.egg-info/SOURCES.txt
registrar.egg-info/dependency_links.txt
registrar.egg-info/not-zip-safe
registrar.egg-info/requires.txt
registrar.egg-info/top_level.txt
registrar/crypto/__init__.py
registrar/crypto/bip38.py
registrar/crypto/utils.py
registrar/drivers/__init__.py
registrar/drivers/api_driver.py
registrar/drivers/webapp_driver.py
tools/__init__.py
tools/csv_reserve.py
tools/migration.py
tools/misc.py
tools/namespace_diff.py
tools/namespace_export.py
tools/namespace_import.py
tools/namespace_state.py
tools/profile_conversion.py
tools/sweep_btc.py
tools/warmup_mirror.py