Metadata-Version: 1.1
Name: registrar
Version: 0.0.3.10
Summary: Blockstack registrar for bulk registrations and updates
Home-page: https://github.com/blockstack/registrar
Author: Blockstack.org
Author-email: support@blockstack.org
License: GPLv3
Download-URL: https://github.com/blockstack/registrar/archive/master.zip
Keywords: blockchain bitcoin BTC cryptocurrency name registrations data
Platform: UNKNOWN
Classifier: Intended Audience :: Developers
Classifier: License :: OSI Approved :: GNU General Public License v3 (GPLv3)
Classifier: Operating System :: OS Independent
Classifier: Programming Language :: Python
Classifier: Topic :: Internet
Classifier: Topic :: Security :: Cryptography
Classifier: Topic :: Software Development :: Libraries :: Python Modules
